reqauto/__init__.py
reqauto/main.py
reqauto-0.1.7.dist-info/METADATA
reqauto-0.1.7.dist-info/WHEEL
reqauto-0.1.7.dist-info/RECORD
