Metadata-Version: 2.1
Name: reqauto
Version: 0.1.7
Summary: A Python package to automatically generate and install requirements.txt
Author: Jaseunda
Author-email: opensource@jaseunda.com
Requires-Python: >=3.6,<4.0
Classifier: Programming Language :: Python :: 3
Classifier: Programming Language :: Python :: 3.6
Classifier: Programming Language :: Python :: 3.7
Classifier: Programming Language :: Python :: 3.8
Classifier: Programming Language :: Python :: 3.9
Classifier: Programming Language :: Python :: 3.10
Classifier: Programming Language :: Python :: 3.11
